grma/__init__.py
grma/grma.py
grma/grma_main.py
grma/main.py
grma/donorsgraph/__init__.py
grma/donorsgraph/build_donors_graph.py
grma/donorsgraph/create_lol.py
grma/match/__init__.py
grma/match/donors_matching.py
grma/match/graph_wrapper.py
grma/match/lol_graph.cpython-311-x86_64-linux-gnu.so
grma/match/lol_graph.pyx
grma/match/match.py
grma/utilities/__init__.py
grma/utilities/cutils.cpython-311-x86_64-linux-gnu.so
grma/utilities/cutils.pyx
grma/utilities/geno_representation.py
grma/utilities/utils.py
py_graph_match_temp-0.0.10.dist-info/LICENSE
py_graph_match_temp-0.0.10.dist-info/METADATA
py_graph_match_temp-0.0.10.dist-info/WHEEL
py_graph_match_temp-0.0.10.dist-info/top_level.txt
py_graph_match_temp-0.0.10.dist-info/RECORD
