Metadata-Version: 2.2
Name: py-graph-match-temp
Version: 0.0.10
Summary: A Python package for graph matching.
Home-page: https://github.com/nmdp-bioinformatics/
Author: Pradeep Bashyal
Author-email: Regev Yehezkel Imra <regevel2006@gmail.com>
License:                    GNU LESSER GENERAL PUBLIC LICENSE
Requires-Python: >=3.8
License-File: LICENSE
Requires-Dist: toml>=0.10.2
Requires-Dist: py-graph-imputation>=0.0.12
Requires-Dist: py-ard>=1.0.9
Requires-Dist: tqdm>=4.66.1
Provides-Extra: tests
Requires-Dist: pytest>=7.1.2; extra == "tests"
Requires-Dist: behave>=1.2.6; extra == "tests"
Requires-Dist: PyHamcrest>=2.0.3; extra == "tests"
Provides-Extra: dev
Requires-Dist: allure-behave>=2.9.45; extra == "dev"
Requires-Dist: flake8>=4.0.1; extra == "dev"
Requires-Dist: bump2version>=1.0.1; extra == "dev"
Requires-Dist: coverage>=6.3.2; extra == "dev"
Requires-Dist: pre-commit>=2.18.1; extra == "dev"
Provides-Extra: deploy
Requires-Dist: connexion[swagger-ui]>=2.13.0; extra == "deploy"
Requires-Dist: gunicorn>=20.1.0; extra == "deploy"
Dynamic: author
Dynamic: home-page
Dynamic: requires-python
